pybird/__init__.py
pybird-1.2.0.dist-info/LICENSE.txt
pybird-1.2.0.dist-info/METADATA
pybird-1.2.0.dist-info/WHEEL
pybird-1.2.0.dist-info/RECORD
